openfisca_nsw_rules_kids_vouchers/__init__.py
openfisca_nsw_rules_kids_vouchers/constants/max_age.yaml
openfisca_nsw_rules_kids_vouchers/constants/min_age.yaml
openfisca_nsw_rules_kids_vouchers/constants/voucher.yaml
openfisca_nsw_rules_kids_vouchers/parameters/active_kids/__init__.py
openfisca_nsw_rules_kids_vouchers/parameters/active_kids/max_age.yaml
openfisca_nsw_rules_kids_vouchers/parameters/active_kids/min_age.yaml
openfisca_nsw_rules_kids_vouchers/parameters/active_kids/voucher.yaml
openfisca_nsw_rules_kids_vouchers/parameters/creative_kids/__init__.py
openfisca_nsw_rules_kids_vouchers/parameters/creative_kids/max_age.yaml
openfisca_nsw_rules_kids_vouchers/parameters/creative_kids/min_age.yaml
openfisca_nsw_rules_kids_vouchers/parameters/creative_kids/voucher.yaml
openfisca_nsw_rules_kids_vouchers/parameters/local_town/__init__.py
openfisca_nsw_rules_kids_vouchers/parameters/local_town/index.yaml
openfisca_nsw_rules_kids_vouchers/parameters/local_town/child_allowance/amount.yaml
openfisca_nsw_rules_kids_vouchers/parameters/local_town/child_allowance/index.yaml
openfisca_nsw_rules_kids_vouchers/tests/creative_families.yaml
openfisca_nsw_rules_kids_vouchers/tests/creative_meets_criteria.yaml
openfisca_nsw_rules_kids_vouchers/tests/creative_meets_criteria_not_active_kids.yaml
openfisca_nsw_rules_kids_vouchers/tests/families.yaml
openfisca_nsw_rules_kids_vouchers/tests/meets_criteria.yaml
openfisca_nsw_rules_kids_vouchers/tests/meets_criteria_not_creative_kids.yaml
openfisca_nsw_rules_kids_vouchers/variables/__init__.py
openfisca_nsw_rules_kids_vouchers/variables/demographics.py
openfisca_nsw_rules_kids_vouchers/variables/education.py
openfisca_nsw_rules_kids_vouchers/variables/relationships.py
openfisca_nsw_rules_kids_vouchers/variables/residential.py
openfisca_nsw_rules_kids_vouchers/variables/entitlement_cards/__init__.py
openfisca_nsw_rules_kids_vouchers/variables/entitlement_cards/concession_card.py
openfisca_nsw_rules_kids_vouchers-1.3.2.dist-info/LICENSE
openfisca_nsw_rules_kids_vouchers-1.3.2.dist-info/METADATA
openfisca_nsw_rules_kids_vouchers-1.3.2.dist-info/WHEEL
openfisca_nsw_rules_kids_vouchers-1.3.2.dist-info/top_level.txt
openfisca_nsw_rules_kids_vouchers-1.3.2.dist-info/RECORD
